LICENSE
README.md
setup.py
yticker/__init__.py
yticker/yaticker_proto.cpp
yticker/yticker.cpp
yticker.egg-info/PKG-INFO
yticker.egg-info/SOURCES.txt
yticker.egg-info/dependency_links.txt
yticker.egg-info/not-zip-safe
yticker.egg-info/requires.txt
yticker.egg-info/top_level.txt