Metadata-Version: 2.1
Name: yticker
Version: 0.1.1
Summary: A Python package for connecting to yahoo websocket.
Home-page: https://github.com/Tapanhaz/yticker
Author: Tapan Hazarika
Author-email: tapanhaz@gmail.com
License: MIT License
Classifier: Programming Language :: Python :: 3
Classifier: License :: OSI Approved :: MIT License
Classifier: Operating System :: OS Independent
License-File: LICENSE
Requires-Dist: cython
Requires-Dist: picows
Requires-Dist: pyrobuf
Requires-Dist: orjson
Requires-Dist: uvloop
